nth_api/__init__.py
nth_api/hashes.py
nth_api-1.3.5.dist-info/LICENSE
nth_api-1.3.5.dist-info/METADATA
nth_api-1.3.5.dist-info/WHEEL
nth_api-1.3.5.dist-info/top_level.txt
nth_api-1.3.5.dist-info/RECORD
