Metadata-Version: 2.1
Name: nth_api
Version: 1.3.5
Summary: Name-That-Hash api version
Home-page: https://github.com/user-sspmynxdvb/nth_api
Author: user-sspmynxdvb
License: GNUv3
Classifier: Programming Language :: Python :: 3
Classifier: Operating System :: OS Independent
Classifier: License :: OSI Approved :: GNU General Public License v3 (GPLv3)
License-File: LICENSE
